cometusb/__init__.py
cometusb/cometusb.py
cometusb-1.0.dist-info/licenses/LICENSE
cometusb-1.0.dist-info/METADATA
cometusb-1.0.dist-info/WHEEL
cometusb-1.0.dist-info/entry_points.txt
cometusb-1.0.dist-info/top_level.txt
cometusb-1.0.dist-info/RECORD
