Metadata-Version: 2.4
Name: cometusb
Version: 1.0
Summary: Create Linux bootable USB from CLI
Author-email: Shahid Rahaman <shahidrahman333@gmail.com>
License-Expression: MIT
Project-URL: Homepage, https://github.com/CometUSB/CometUSB
Project-URL: Documentation, https://CometUSB.github.io/CometUSB/
Project-URL: Changelog, https://github.com/CometUSB/CometUSB/releases
Requires-Python: >=3.8
License-File: LICENSE
Requires-Dist: requests
Requires-Dist: tqdm
Requires-Dist: tabulate
Dynamic: license-file
